pyunitsconverter/__init__.py
pyunitsconverter/amperage.py
pyunitsconverter/area.py
pyunitsconverter/energy.py
pyunitsconverter/frequency.py
pyunitsconverter/length.py
pyunitsconverter/mass.py
pyunitsconverter/power.py
pyunitsconverter/pressure.py
pyunitsconverter/speed.py
pyunitsconverter/temperature.py
pyunitsconverter/time.py
pyunitsconverter/voltage.py
pyunitsconverter/volume.py
pyunitsconverter-0.1.4.dist-info/LICENSE.txt
pyunitsconverter-0.1.4.dist-info/METADATA
pyunitsconverter-0.1.4.dist-info/WHEEL
pyunitsconverter-0.1.4.dist-info/top_level.txt
pyunitsconverter-0.1.4.dist-info/RECORD
