Metadata-Version: 2.1
Name: pyunitsconverter
Version: 0.1.4
Summary: A package for easy unit conversions
Home-page: http://pypi.python.org/pypi/pyunitsconverter/
Author: Sven Eschlbeck
Author-email: sven.eschlbeck@t-online.de
License: LICENSE.txt
Platform: UNKNOWN
License-File: LICENSE.txt
